[
	{
		"id": 14,
		"type": "manual",
		"icon": "https://assets.aithercol.com/wallet/payment-icons/bank.png",
		"name": "Банковский счет (Russia)",
		"fields": [
			{
				"type": "string",
				"name": "name",
				"display_name": "ФИО"
			},
			{
				"type": "string",
				"name": "bik",
				"display_name": "БИК"
			},
			{
				"type": "string",
				"name": "corr_account",
				"display_name": "Корр.счёт"
			},
			{
				"type": "string",
				"name": "account",
				"display_name": "Расчётный счёт"
			}
		],
		"min_amount": 1,
		"max_amount": 10000000,
		"commission": {
			"percent": 2,
			"amount": 120
		},
		"long_wait": false,
		"currency": "RUB"
	}
]
