{"id":13378,"username":"dirtybot","overvall_playtime":14242,"launches_count":10,"friends_count":1,"top_launch_dates":[{"date":"10/30/2023","launches":4},{"date":"09/10/2023","launches":3},{"date":"10/31/2023","launches":2},{"date":"10/29/2023","launches":1}],"friends":[{"id":13379,"username":"dirtyrio","created_at":"2023-11-14T10:47:57.000+00:00"}],"top_versions":[{"version":"1.8.9","launches":7},{"version":"1.8","launches":3}],"spent":0,"payments_count":0,"top_server_joins":[],"server_joins_count":0}