{"id":15089,"username":"WrongLeon","overvall_playtime":566873,"launches_count":185,"friends_count":0,"top_launch_dates":[{"date":"12/09/2023","launches":6},{"date":"12/01/2023","launches":6},{"date":"11/05/2023","launches":6},{"date":"12/17/2023","launches":5},{"date":"12/08/2023","launches":5}],"friends":[],"top_versions":[{"version":"1.8","launches":159},{"version":"1.8.9","launches":26}],"spent":0,"payments_count":0,"top_server_joins":[{"server_ip":"nektax.net","joins":13},{"server_ip":"play.pikanetwork.net","joins":9},{"server_ip":"blocksmc.com","joins":6},{"server_ip":"edenmine.eu","joins":3},{"server_ip":"hylexmc.net","joins":2}],"server_joins_count":41}