{"id":18659,"username":"DanilkaProBro","overvall_playtime":203031,"launches_count":81,"friends_count":0,"top_launch_dates":[{"date":"12/09/2023","launches":9},{"date":"12/23/2023","launches":8},{"date":"12/18/2023","launches":6},{"date":"12/12/2023","launches":6},{"date":"12/11/2023","launches":6}],"friends":[],"top_versions":[{"version":"1.8","launches":81}],"spent":0,"payments_count":0,"top_server_joins":[{"server_ip":"mc.gamster.org","joins":12},{"server_ip":"twerion.net","joins":1},{"server_ip":"ruhypixel.net","joins":1}],"server_joins_count":14}