{"id":22811,"username":"Fffgeww228","overvall_playtime":57384,"launches_count":23,"friends_count":0,"top_launch_dates":[{"date":"12/02/2023","launches":4},{"date":"12/17/2023","launches":3},{"date":"12/23/2023","launches":2},{"date":"12/22/2023","launches":2},{"date":"12/15/2023","launches":2}],"friends":[],"top_versions":[{"version":"1.8","launches":23}],"spent":0,"payments_count":0,"top_server_joins":[{"server_ip":"mc.masedworld.net","joins":4},{"server_ip":"twerion.net","joins":1}],"server_joins_count":5}