{"id":23974,"username":"krutoi_artem1337","overvall_playtime":47009,"launches_count":28,"friends_count":0,"top_launch_dates":[{"date":"12/24/2023","launches":8},{"date":"12/20/2023","launches":3},{"date":"12/03/2023","launches":3},{"date":"12/23/2023","launches":2},{"date":"12/22/2023","launches":2}],"friends":[],"top_versions":[{"version":"1.8","launches":26},{"version":"1.8.9","launches":2}],"spent":0,"payments_count":0,"top_server_joins":[{"server_ip":"mineblaze.ru","joins":12}],"server_joins_count":12}