{"id":24278,"username":"nicolisto1314","overvall_playtime":151079,"launches_count":35,"friends_count":0,"top_launch_dates":[{"date":"12/22/2023","launches":5},{"date":"12/11/2023","launches":4},{"date":"12/23/2023","launches":3},{"date":"12/15/2023","launches":3},{"date":"12/04/2023","launches":3}],"friends":[],"top_versions":[{"version":"1.8","launches":35}],"spent":0,"payments_count":0,"top_server_joins":[{"server_ip":"mc.universocraft.com","joins":3},{"server_ip":"mc.hycraft.us","joins":2}],"server_joins_count":5}