{"id":30130,"username":"Sil4ncixn_","overvall_playtime":129410,"launches_count":48,"friends_count":0,"top_launch_dates":[{"date":"12/17/2023","launches":10},{"date":"12/22/2023","launches":6},{"date":"12/18/2023","launches":6},{"date":"12/16/2023","launches":6},{"date":"12/15/2023","launches":5}],"friends":[],"top_versions":[{"version":"1.8","launches":48}],"spent":0,"payments_count":0,"top_server_joins":[{"server_ip":"mineblaze.ru","joins":26},{"server_ip":"dexland.ru","joins":14},{"server_ip":"mc.vimemc.ru","joins":2},{"server_ip":"mc.gamster.org","joins":1},{"server_ip":"hypixel.net","joins":1}],"server_joins_count":44}