{"id":31017,"username":"siyerr","overvall_playtime":58193,"launches_count":34,"friends_count":0,"top_launch_dates":[{"date":"12/20/2023","launches":11},{"date":"12/21/2023","launches":7},{"date":"12/19/2023","launches":5},{"date":"12/24/2023","launches":4},{"date":"12/16/2023","launches":4}],"friends":[],"top_versions":[{"version":"1.8","launches":34}],"spent":0,"payments_count":0,"top_server_joins":[{"server_ip":"mc.masedworld.net","joins":5},{"server_ip":"play.pikanetwork.net","joins":1}],"server_joins_count":6}