{"id":32260,"username":"amirhosein1213","overvall_playtime":69777,"launches_count":41,"friends_count":0,"top_launch_dates":[{"date":"12/17/2023","launches":12},{"date":"12/18/2023","launches":8},{"date":"12/23/2023","launches":5},{"date":"12/22/2023","launches":5},{"date":"12/24/2023","launches":3}],"friends":[],"top_versions":[{"version":"1.8","launches":41}],"spent":0,"payments_count":0,"top_server_joins":[{"server_ip":"play.lunamc.ir","joins":18},{"server_ip":"play.trexmine.com","joins":7},{"server_ip":"play.madgames.ir","joins":3},{"server_ip":"mc.gamster.org","joins":2},{"server_ip":"mc.gameup.ir","joins":2}],"server_joins_count":38}