{"id":33994,"username":"Gehzer_XD","overvall_playtime":81317,"launches_count":28,"friends_count":0,"top_launch_dates":[{"date":"12/24/2023","launches":7},{"date":"12/20/2023","launches":6},{"date":"12/25/2023","launches":5},{"date":"12/26/2023","launches":3},{"date":"12/23/2023","launches":3}],"friends":[],"top_versions":[{"version":"1.8","launches":28}],"spent":0,"payments_count":0,"top_server_joins":[{"server_ip":"astralmc.cc","joins":18},{"server_ip":"ghostly.live","joins":3},{"server_ip":"mc.minelatino.com","joins":2},{"server_ip":"play.zonecraft.es","joins":2},{"server_ip":"mc.universocraft.com","joins":2}],"server_joins_count":32}