{"id":4857,"username":"davinkk11","overvall_playtime":60761,"launches_count":26,"friends_count":1,"top_launch_dates":[{"date":"06/13/2023","launches":8},{"date":"10/15/2023","launches":5},{"date":"10/16/2023","launches":3},{"date":"10/14/2023","launches":3},{"date":"07/07/2023","launches":3}],"friends":[{"id":14269,"username":"nometerra2007","created_at":"2023-10-16T09:57:20.000+00:00"}],"top_versions":[{"version":"unknown","launches":12},{"version":"1.8","launches":9},{"version":"1.8.9","launches":5}],"spent":0,"payments_count":0,"top_server_joins":[],"server_joins_count":0}