{"id":8011,"username":"Danilxxx229","overvall_playtime":108796,"launches_count":14,"friends_count":0,"top_launch_dates":[{"date":"07/19/2023","launches":3},{"date":"11/04/2023","launches":2},{"date":"07/18/2023","launches":2},{"date":"12/02/2023","launches":1},{"date":"10/18/2023","launches":1}],"friends":[],"top_versions":[{"version":"unknown","launches":7},{"version":"1.8","launches":4},{"version":"1.8.9","launches":3}],"spent":0,"payments_count":0,"top_server_joins":[],"server_joins_count":0}