{"id":8172,"username":"yumeqo__","overvall_playtime":459327,"launches_count":328,"friends_count":0,"top_launch_dates":[{"date":"11/17/2023","launches":36},{"date":"07/24/2023","launches":24},{"date":"07/21/2023","launches":13},{"date":"11/19/2023","launches":11},{"date":"08/03/2023","launches":11}],"friends":[],"top_versions":[{"version":"1.8","launches":187},{"version":"unknown","launches":76},{"version":"1.8.9","launches":65}],"spent":880,"payments_count":8,"top_server_joins":[{"server_ip":"weakestww.ru","joins":6},{"server_ip":"freadenred.gomc.fun","joins":1},{"server_ip":"f1.rustix.su","joins":1},{"server_ip":"ebe0cf14-502e-45c5-b61b-f44ef88a05aa.shield.neoprotect.ovh","joins":1}],"server_joins_count":9}