{"id":8184,"username":"qpIoHa001","overvall_playtime":779772,"launches_count":227,"friends_count":0,"top_launch_dates":[{"date":"12/17/2023","launches":13},{"date":"10/28/2023","launches":11},{"date":"12/23/2023","launches":10},{"date":"11/22/2023","launches":10},{"date":"11/26/2023","launches":8}],"friends":[],"top_versions":[{"version":"1.8","launches":200},{"version":"1.8.9","launches":27}],"spent":0,"payments_count":0,"top_server_joins":[{"server_ip":"mc.ruhypixel.net","joins":21},{"server_ip":"dexland.ru","joins":2}],"server_joins_count":23}